titraxconverter.py
titraxconverter-1.0.0.dist-info/entry_points.txt
titraxconverter-1.0.0.dist-info/LICENSE
titraxconverter-1.0.0.dist-info/WHEEL
titraxconverter-1.0.0.dist-info/METADATA
titraxconverter-1.0.0.dist-info/RECORD
