Metadata-Version: 2.1
Name: titraxconverter
Version: 1.0.0
Summary: Parse TimeTracker time worksheets and add start and endtime to each task
Author-email: Hanne Moa <hanne.moa@sikt.no>
Requires-Python: >=3.8
Classifier: License :: OSI Approved :: MIT License
Project-URL: Home, https://github.com/hmpf/titraxconverter
